{
    "Ar36": {
        "error": 0.002517724107662263,
        "error_type": "",
        "fit": "previous",
        "references": [
            {
                "exclude": false,
                "record_id": "bu-FC-J-12945"
            }
        ],
        "value": 0.0029238314390458834
    },
    "Ar37": {
        "error": 0.03102711852210193,
        "error_type": "",
        "fit": "previous",
        "references": [
            {
                "exclude": false,
                "record_id": "bu-FC-J-12945"
            }
        ],
        "value": 0.07872694808707761
    },
    "Ar38": {
        "error": 0.015668577309463003,
        "error_type": "",
        "fit": "previous",
        "references": [
            {
                "exclude": false,
                "record_id": "bu-FC-J-12945"
            }
        ],
        "value": 0.050433700185193706
    },
    "Ar39": {
        "error": 0.17341372094328533,
        "error_type": "",
        "fit": "previous",
        "references": [
            {
                "exclude": false,
                "record_id": "bu-FC-J-12945"
            }
        ],
        "value": 0.02631374596096326
    },
    "Ar40": {
        "error": 0.1473423894415693,
        "error_type": "",
        "fit": "previous",
        "references": [
            {
                "exclude": false,
                "record_id": "bu-FC-J-12945"
            }
        ],
        "value": 1.227755343717131
    },
    "Ar41": {
        "error": 0.02020990795871618,
        "error_type": "",
        "fit": "previous",
        "references": [
            {
                "exclude": false,
                "record_id": "bu-FC-J-12945"
            }
        ],
        "value": 0.07219760823345335
    }
}