{
    "AX": {
        "error": 0.007072511451411429,
        "error_type": "SEM",
        "filter_outliers_dict": {
            "filter_outliers": true,
            "iterations": 1,
            "std_devs": 2
        },
        "fit": "average",
        "value": -0.040026173630972765
    },
    "CDD": {
        "error": 1.7516088222317363e-05,
        "error_type": "SEM",
        "filter_outliers_dict": {
            "filter_outliers": true,
            "iterations": 1,
            "std_devs": 10
        },
        "fit": "average",
        "value": 0.0001068670531412439
    },
    "H1": {
        "error": 0.004936148031831598,
        "error_type": "SEM",
        "filter_outliers_dict": {
            "filter_outliers": true,
            "iterations": 1,
            "std_devs": 2
        },
        "fit": "average",
        "value": 0.021655268078504233
    },
    "H2": {
        "error": 0.0029879956883008168,
        "error_type": "SEM",
        "filter_outliers_dict": {
            "filter_outliers": true,
            "iterations": 1,
            "std_devs": 2
        },
        "fit": "average",
        "value": 0.0868501439918412
    },
    "L1": {
        "error": 0.0027761885868080468,
        "error_type": "SEM",
        "filter_outliers_dict": {
            "filter_outliers": true,
            "iterations": 1,
            "std_devs": 2
        },
        "fit": "average",
        "value": 0.0008078472698208318
    },
    "L2": {
        "error": 0.0030722925960214786,
        "error_type": "SEM",
        "filter_outliers_dict": {
            "filter_outliers": true,
            "iterations": 1,
            "std_devs": 2
        },
        "fit": "average",
        "value": -0.004307005290392245
    }
}