{
    "Ar36": {
        "error": 0.0001251517930799028, 
        "fit": "previous", 
        "references": [
            {
                "exclude": false, 
                "runid": "bu-FC-J-6787"
            }
        ], 
        "value": 0.002360256661203809
    }, 
    "Ar37": {
        "error": 0.005052974735083994, 
        "fit": "previous", 
        "references": [
            {
                "exclude": false, 
                "runid": "bu-FC-J-6787"
            }
        ], 
        "value": 0.023079702724478318
    }, 
    "Ar38": {
        "error": 0.0021381421686868275, 
        "fit": "previous", 
        "references": [
            {
                "exclude": false, 
                "runid": "bu-FC-J-6787"
            }
        ], 
        "value": 0.008446400395540427
    }, 
    "Ar39": {
        "error": 0.00896092577279056, 
        "fit": "previous", 
        "references": [
            {
                "exclude": false, 
                "runid": "bu-FC-J-6787"
            }
        ], 
        "value": 0.0010290735898312725
    }, 
    "Ar40": {
        "error": 0.007063789811216439, 
        "fit": "previous", 
        "references": [
            {
                "exclude": false, 
                "runid": "bu-FC-J-6787"
            }
        ], 
        "value": 0.5320300338693056
    }, 
    "Ar41": {
        "error": 0.0053331473331277345, 
        "fit": "previous", 
        "references": [
            {
                "exclude": false, 
                "runid": "bu-FC-J-6787"
            }
        ], 
        "value": -0.007232013487415534
    }
}